{"movie_details": {"movie": {"id": 20956, "url": "https://yts.mx/movies/go-go-sisters-2018", "imdb_code": "tt8081638", "title": "Go-Go Sisters", "title_english": "Go-Go Sisters", "title_long": "Go-Go Sisters (2018)", "slug": "go-go-sisters-2018", "year": 2018, "rating": 7.2, "runtime": 118, "genres": ["Action", "Comedy", "Drama"], "download_count": 4747, "like_count": 3, "description_intro": "Go-go sisters brings together two parallel stories about young ambitious teenage girls and middle-aged women who have experienced life's sweet spiciness.", "description_full": "Go-go sisters brings together two parallel stories about young ambitious teenage girls and middle-aged women who have experienced life's sweet spiciness.", "yt_trailer_code": "", "language": "vi", "mpa_rating": "", "background_image": "https://yts.mx/assets/images/movies/go_go_sisters_2018/background.jpg", "background_image_original": "https://yts.mx/assets/images/movies/go_go_sisters_2018/background.jpg", "small_cover_image": "https://yts.mx/assets/images/movies/go_go_sisters_2018/small-cover.jpg", "medium_cover_image": "https://yts.mx/assets/images/movies/go_go_sisters_2018/medium-cover.jpg", "large_cover_image": "https://yts.mx/assets/images/movies/go_go_sisters_2018/large-cover.jpg", "medium_screenshot_image1": "https://yts.mx/assets/images/movies/go_go_sisters_2018/medium-screenshot1.jpg", "medium_screenshot_image2": "https://yts.mx/assets/images/movies/go_go_sisters_2018/medium-screenshot2.jpg", "medium_screenshot_image3": "https://yts.mx/assets/images/movies/go_go_sisters_2018/medium-screenshot3.jpg", "large_screenshot_image1": "https://yts.mx/assets/images/movies/go_go_sisters_2018/large-screenshot1.jpg", "large_screenshot_image2": "https://yts.mx/assets/images/movies/go_go_sisters_2018/large-screenshot2.jpg", "large_screenshot_image3": "https://yts.mx/assets/images/movies/go_go_sisters_2018/large-screenshot3.jpg", "torrents": [{"url": "https://yts.mx/torrent/download/3A9C4DA6A3FC20587BCE0B3B8EB4B0BE05C64809", "hash": "3A9C4DA6A3FC20587BCE0B3B8EB4B0BE05C64809", "quality": "720p", "type": "web", "seeds": 2, "peers": 1, "size": "1.05 GB", "size_bytes": 1127428915, "date_uploaded": "2020-09-06 11:08:31", "date_uploaded_unix": 1599383311}, {"url": "https://yts.mx/torrent/download/FB1C2F53E3B60A5D1B093078C834AA7A06EA60E8", "hash": "FB1C2F53E3B60A5D1B093078C834AA7A06EA60E8", "quality": "1080p", "type": "web", "seeds": 3, "peers": 3, "size": "2.16 GB", "size_bytes": 2319282340, "date_uploaded": "2020-09-06 13:36:20", "date_uploaded_unix": 1599392180}], "date_uploaded": "2020-09-06 11:08:31", "date_uploaded_unix": 1599383311}}, "movie_suggestions": {"movie_count": 4, "movies": [{"id": 10168, "url": "https://yts.mx/movies/backtrace-2018", "imdb_code": "tt3588588", "title": "Backtrace", "title_english": "Backtrace", "title_long": "Backtrace (2018)", "slug": "backtrace-2018", "year": 2018, "rating": 3.8, "runtime": 92, "genres": ["Action", "Crime", "Drama"], "summary": "The lone surviving thief of a violent armored car robbery is sprung from a high security facility and administered an experimental drug.", "description_full": "The lone surviving thief of a violent armored car robbery is sprung from a high security facility and administered an experimental drug.", "synopsis": "The lone surviving thief of a violent armored car robbery is sprung from a high security facility and administered an experimental drug.", "yt_trailer_code": "INDleu1aHyE", "language": "en", "mpa_rating": "R", "background_image": "https://yts.mx/assets/images/movies/backtrace_2018/background.jpg", "background_image_original": "https://yts.mx/assets/images/movies/backtrace_2018/background.jpg", "small_cover_image": "https://yts.mx/assets/images/movies/backtrace_2018/small-cover.jpg", "medium_cover_image": "https://yts.mx/assets/images/movies/backtrace_2018/medium-cover.jpg", "state": "ok", "torrents": [{"url": "https://yts.mx/torrent/download/77EF461700D98F319CCF017969FB141321EE47F4", "hash": "77EF461700D98F319CCF017969FB141321EE47F4", "quality": "720p", "seeds": 16, "peers": 1, "size": "760.32 MB", "size_bytes": 797253304, "date_uploaded": "2019-02-15 08:54:19", "date_uploaded_unix": 1550217259}, {"url": "https://yts.mx/torrent/download/2D9098FFBD0A85B2E0BB9A3D94771162450E02C9", "hash": "2D9098FFBD0A85B2E0BB9A3D94771162450E02C9", "quality": "1080p", "seeds": 5, "peers": 4, "size": "1.41 GB", "size_bytes": 1513975972, "date_uploaded": "2019-02-15 11:00:45", "date_uploaded_unix": 1550224845}, {"url": "https://yts.mx/torrent/download/1660963F22E6324C650594BF13766E081CACFF92", "hash": "1660963F22E6324C650594BF13766E081CACFF92", "quality": "720p", "seeds": 7, "peers": 4, "size": "752.97 MB", "size_bytes": 789546271, "date_uploaded": "2018-12-15 00:03:40", "date_uploaded_unix": 1544828620}, {"url": "https://yts.mx/torrent/download/81C876987E78308E1E0370D7DF0EAC1EDBA07DB8", "hash": "81C876987E78308E1E0370D7DF0EAC1EDBA07DB8", "quality": "1080p", "seeds": 5, "peers": 4, "size": "1.41 GB", "size_bytes": 1513975972, "date_uploaded": "2018-12-15 01:48:37", "date_uploaded_unix": 1544834917}], "date_uploaded": "2018-12-15 00:03:40", "date_uploaded_unix": 1544828620}, {"id": 8616, "url": "https://yts.mx/movies/down-a-dark-hall-2018", "imdb_code": "tt2372251", "title": "Down a Dark Hall", "title_english": "Down a Dark Hall", "title_long": "Down a Dark Hall (2018)", "slug": "down-a-dark-hall-2018", "year": 2018, "rating": 5.1, "runtime": 96, "genres": ["Action", "Drama", "Fantasy", "Horror", "Mystery", "Thriller"], "summary": "After the death of her father when she was a child, Kit Gordy has grown up as a troubled teen for disgust of her mother Ginny and her stepfather Dave Dabrowski. Called to the principal's office of her high school and accused of a failed attempt to burn it, Kit is expelled from the high school, but Dr. Heather Sinclair, member of the staff of the Blackwood Boarding School, appears to offer her a place in the next school year. Ginny enlists Kit against her will in a try to correct her daughter, and Kit travels Blackwood, an old, isolated and dark mansion in the middle of a forest outside the city. There she meets her companions: nice Izzy, shy Ashley, reluctant Sierra and borderline Veronica, so troubled teens as her own. In the dinner presentation, Kit and the other girls meet Madame Duret, Blackwood's headmistress, and the rest of the staff: Pr. Farley (maths), Jules Duret (music), Heather Sinclair (arts) and Mrs. Olonsky, Madame Duret's rude right-hand to keep the peace in Blackwood....", "description_full": "After the death of her father when she was a child, Kit Gordy has grown up as a troubled teen for disgust of her mother Ginny and her stepfather Dave Dabrowski. Called to the principal's office of her high school and accused of a failed attempt to burn it, Kit is expelled from the high school, but Dr. Heather Sinclair, member of the staff of the Blackwood Boarding School, appears to offer her a place in the next school year. Ginny enlists Kit against her will in a try to correct her daughter, and Kit travels Blackwood, an old, isolated and dark mansion in the middle of a forest outside the city. There she meets her companions: nice Izzy, shy Ashley, reluctant Sierra and borderline Veronica, so troubled teens as her own. In the dinner presentation, Kit and the other girls meet Madame Duret, Blackwood's headmistress, and the rest of the staff: Pr. Farley (maths), Jules Duret (music), Heather Sinclair (arts) and Mrs. Olonsky, Madame Duret's rude right-hand to keep the peace in Blackwood....", "synopsis": "After the death of her father when she was a child, Kit Gordy has grown up as a troubled teen for disgust of her mother Ginny and her stepfather Dave Dabrowski. Called to the principal's office of her high school and accused of a failed attempt to burn it, Kit is expelled from the high school, but Dr. Heather Sinclair, member of the staff of the Blackwood Boarding School, appears to offer her a place in the next school year. Ginny enlists Kit against her will in a try to correct her daughter, and Kit travels Blackwood, an old, isolated and dark mansion in the middle of a forest outside the city. There she meets her companions: nice Izzy, shy Ashley, reluctant Sierra and borderline Veronica, so troubled teens as her own. In the dinner presentation, Kit and the other girls meet Madame Duret, Blackwood's headmistress, and the rest of the staff: Pr. Farley (maths), Jules Duret (music), Heather Sinclair (arts) and Mrs. Olonsky, Madame Duret's rude right-hand to keep the peace in Blackwood....", "yt_trailer_code": "TwHoY2dVZLE", "language": "en", "mpa_rating": "PG-13", "background_image": "https://yts.mx/assets/images/movies/down_a_dark_hall_2018/background.jpg", "background_image_original": "https://yts.mx/assets/images/movies/down_a_dark_hall_2018/background.jpg", "small_cover_image": "https://yts.mx/assets/images/movies/down_a_dark_hall_2018/small-cover.jpg", "medium_cover_image": "https://yts.mx/assets/images/movies/down_a_dark_hall_2018/medium-cover.jpg", "state": "ok", "torrents": [{"url": "https://yts.mx/torrent/download/A8B32DAE56E6381F92719BC499D917F07B8653C5", "hash": "A8B32DAE56E6381F92719BC499D917F07B8653C5", "quality": "720p", "seeds": 13, "peers": 2, "size": "819.02 MB", "size_bytes": 858804716, "date_uploaded": "2018-10-15 04:01:02", "date_uploaded_unix": 1539568862}, {"url": "https://yts.mx/torrent/download/F1962C56D0C7B171DD308EEAE2270E53499A526E", "hash": "F1962C56D0C7B171DD308EEAE2270E53499A526E", "quality": "1080p", "seeds": 9, "peers": 4, "size": "1.54 GB", "size_bytes": 1653562409, "date_uploaded": "2018-10-15 05:48:18", "date_uploaded_unix": 1539575298}, {"url": "https://yts.mx/torrent/download/DC287EFF91AAAB4B4436CD24DA0030B1D55D2215", "hash": "DC287EFF91AAAB4B4436CD24DA0030B1D55D2215", "quality": "720p", "seeds": 7, "peers": 4, "size": "816.24 MB", "size_bytes": 855889674, "date_uploaded": "2018-08-18 19:43:32", "date_uploaded_unix": 1534614212}, {"url": "https://yts.mx/torrent/download/8F75C7625402F83F3B6C834750AB07F9FBDF3D03", "hash": "8F75C7625402F83F3B6C834750AB07F9FBDF3D03", "quality": "1080p", "seeds": 9, "peers": 1, "size": "1.54 GB", "size_bytes": 1653562409, "date_uploaded": "2018-08-18 21:21:42", "date_uploaded_unix": 1534620102}], "date_uploaded": "2018-08-18 19:43:32", "date_uploaded_unix": 1534614212}, {"id": 10039, "url": "https://yts.mx/movies/a-fistful-of-lead-2018", "imdb_code": "tt7468604", "title": "A Fistful of Lead", "title_english": "A Fistful of Lead", "title_long": "A Fistful of Lead (2018)", "slug": "a-fistful-of-lead-2018", "year": 2018, "rating": 3.7, "runtime": 86, "genres": ["Action", "Western"], "summary": "Four of the West's most infamous outlaws carry out a daring bank heist in the gold-rush town, Bath Water. As the posse takes chase, things take a turn for the worse, as the bandits realize they've been double-crossed - but by who?", "description_full": "Four of the West's most infamous outlaws carry out a daring bank heist in the gold-rush town, Bath Water. As the posse takes chase, things take a turn for the worse, as the bandits realize they've been double-crossed - but by who?", "synopsis": "Four of the West's most infamous outlaws carry out a daring bank heist in the gold-rush town, Bath Water. As the posse takes chase, things take a turn for the worse, as the bandits realize they've been double-crossed - but by who?", "yt_trailer_code": "cqnlPPQo2_g", "language": "en", "mpa_rating": "", "background_image": "https://yts.mx/assets/images/movies/a_fistful_of_lead_2018/background.jpg", "background_image_original": "https://yts.mx/assets/images/movies/a_fistful_of_lead_2018/background.jpg", "small_cover_image": "https://yts.mx/assets/images/movies/a_fistful_of_lead_2018/small-cover.jpg", "medium_cover_image": "https://yts.mx/assets/images/movies/a_fistful_of_lead_2018/medium-cover.jpg", "state": "ok", "torrents": [{"url": "https://yts.mx/torrent/download/F754C408BD506FC275E3CB176BC4D1F144E62F60", "hash": "F754C408BD506FC275E3CB176BC4D1F144E62F60", "quality": "720p", "seeds": 1, "peers": 0, "size": "746.08 MB", "size_bytes": 782321582, "date_uploaded": "2018-12-05 01:21:56", "date_uploaded_unix": 1543969316}, {"url": "https://yts.mx/torrent/download/F357F5820A501DC72951332185B0878AE15E8137", "hash": "F357F5820A501DC72951332185B0878AE15E8137", "quality": "1080p", "seeds": 2, "peers": 4, "size": "1.39 GB", "size_bytes": 1492501135, "date_uploaded": "2018-12-05 02:46:23", "date_uploaded_unix": 1543974383}], "date_uploaded": "2018-12-05 01:21:56", "date_uploaded_unix": 1543969316}, {"id": 10156, "url": "https://yts.mx/movies/a-boy-a-girl-a-dream-2018", "imdb_code": "tt6905402", "title": "A Boy. A Girl. A Dream.", "title_english": "A Boy. A Girl. A Dream.", "title_long": "A Boy. A Girl. A Dream. (2018)", "slug": "a-boy-a-girl-a-dream-2018", "year": 2018, "rating": 4.7, "runtime": 89, "genres": ["Action", "Drama", "Romance"], "summary": "On the night of the 2016 Presidential election, Cass, an L.A. club promoter, takes a thrilling and emotional journey with Frida, a Midwestern visitor. She challenges him to revisit his broken dreams - while he pushes her to discover hers.", "description_full": "On the night of the 2016 Presidential election, Cass, an L.A. club promoter, takes a thrilling and emotional journey with Frida, a Midwestern visitor. She challenges him to revisit his broken dreams - while he pushes her to discover hers.", "synopsis": "On the night of the 2016 Presidential election, Cass, an L.A. club promoter, takes a thrilling and emotional journey with Frida, a Midwestern visitor. She challenges him to revisit his broken dreams - while he pushes her to discover hers.", "yt_trailer_code": "_ZHQUj-CJPo", "language": "en", "mpa_rating": "R", "background_image": "https://yts.mx/assets/images/movies/a_boy_a_girl_a_dream_2018/background.jpg", "background_image_original": "https://yts.mx/assets/images/movies/a_boy_a_girl_a_dream_2018/background.jpg", "small_cover_image": "https://yts.mx/assets/images/movies/a_boy_a_girl_a_dream_2018/small-cover.jpg", "medium_cover_image": "https://yts.mx/assets/images/movies/a_boy_a_girl_a_dream_2018/medium-cover.jpg", "state": "ok", "torrents": [{"url": "https://yts.mx/torrent/download/489CDDA8584796AAFE2DA873F7133D54076389D6", "hash": "489CDDA8584796AAFE2DA873F7133D54076389D6", "quality": "720p", "seeds": 4, "peers": 1, "size": "773.63 MB", "size_bytes": 811209851, "date_uploaded": "2018-12-13 22:37:09", "date_uploaded_unix": 1544737029}, {"url": "https://yts.mx/torrent/download/D373F033680FCFF741A6DC9291348670DA573147", "hash": "D373F033680FCFF741A6DC9291348670DA573147", "quality": "1080p", "seeds": 4, "peers": 0, "size": "1.44 GB", "size_bytes": 1546188227, "date_uploaded": "2018-12-13 23:52:45", "date_uploaded_unix": 1544741565}], "date_uploaded": "2018-12-13 22:37:09", "date_uploaded_unix": 1544737029}]}}