{"movie_details": {"movie": {"id": 21308, "url": "https://yts.mx/movies/sgt-peppers-lonely-hearts-club-band-1978", "imdb_code": "tt0078239", "title": "Sgt. Pepper's Lonely Hearts Club Band", "title_english": "Sgt. Pepper's Lonely Hearts Club Band", "title_long": "Sgt. Pepper's Lonely Hearts Club Band (1978)", "slug": "sgt-peppers-lonely-hearts-club-band-1978", "year": 1978, "rating": 4.2, "runtime": 113, "genres": ["Adventure", "Comedy", "Fantasy", "Musical"], "download_count": 9393, "like_count": 4, "description_intro": "Ever since they were sent into World War I battle in 1918, Sergeant Pepper and his Lonely Hearts Club Band of Heartland, USA have been spreading the message of joy and love to the world, which has made them and Heartland famous. Upon Sergeant Pepper's death in 1958, the band's instruments have been housed on display at Heartland City Hall as symbols of that love and joy. Before his death, Sergeant Pepper asked his adolescent grandson Billy Shears to take on the reins of forming his own band to continue to spread the message of joy and love. With Billy's brother Dougie Shears as their Manager, Billy, now an adult, and his three best friends, brothers Mark, Dave, and Bob Henderson, embark on their lives as a new Lonely Hearts Club Band. They quickly come to the attention of Hollywood music producer B.D. Hoffler Of B.D. (Big Deal) Records. With the boys off to Hollywood to spread the words of joy and love to the world, enter into Heartland the evil and demented Mr. Mustard, an ex-real ...", "description_full": "Ever since they were sent into World War I battle in 1918, Sergeant Pepper and his Lonely Hearts Club Band of Heartland, USA have been spreading the message of joy and love to the world, which has made them and Heartland famous. Upon Sergeant Pepper's death in 1958, the band's instruments have been housed on display at Heartland City Hall as symbols of that love and joy. Before his death, Sergeant Pepper asked his adolescent grandson Billy Shears to take on the reins of forming his own band to continue to spread the message of joy and love. With Billy's brother Dougie Shears as their Manager, Billy, now an adult, and his three best friends, brothers Mark, Dave, and Bob Henderson, embark on their lives as a new Lonely Hearts Club Band. They quickly come to the attention of Hollywood music producer B.D. Hoffler Of B.D. (Big Deal) Records. With the boys off to Hollywood to spread the words of joy and love to the world, enter into Heartland the evil and demented Mr. Mustard, an ex-real ...", "yt_trailer_code": "PQf5Q9NQvhA", "language": "en", "mpa_rating": "", "background_image": "https://yts.mx/assets/images/movies/sgt_peppers_lonely_hearts_club_band_1978/background.jpg", "background_image_original": "https://yts.mx/assets/images/movies/sgt_peppers_lonely_hearts_club_band_1978/background.jpg", "small_cover_image": "https://yts.mx/assets/images/movies/sgt_peppers_lonely_hearts_club_band_1978/small-cover.jpg", "medium_cover_image": "https://yts.mx/assets/images/movies/sgt_peppers_lonely_hearts_club_band_1978/medium-cover.jpg", "large_cover_image": "https://yts.mx/assets/images/movies/sgt_peppers_lonely_hearts_club_band_1978/large-cover.jpg", "medium_screenshot_image1": "https://yts.mx/assets/images/movies/sgt_peppers_lonely_hearts_club_band_1978/medium-screenshot1.jpg", "medium_screenshot_image2": "https://yts.mx/assets/images/movies/sgt_peppers_lonely_hearts_club_band_1978/medium-screenshot2.jpg", "medium_screenshot_image3": "https://yts.mx/assets/images/movies/sgt_peppers_lonely_hearts_club_band_1978/medium-screenshot3.jpg", "large_screenshot_image1": "https://yts.mx/assets/images/movies/sgt_peppers_lonely_hearts_club_band_1978/large-screenshot1.jpg", "large_screenshot_image2": "https://yts.mx/assets/images/movies/sgt_peppers_lonely_hearts_club_band_1978/large-screenshot2.jpg", "large_screenshot_image3": "https://yts.mx/assets/images/movies/sgt_peppers_lonely_hearts_club_band_1978/large-screenshot3.jpg", "cast": [{"name": "George Burns", "character_name": "Mr. Kite", "url_small_image": "https://yts.mx/assets/images/actors/thumb/nm0122675.jpg", "imdb_code": "0122675"}, {"name": "Steve Martin", "character_name": "Dr. Maxwell Edison", "url_small_image": "https://yts.mx/assets/images/actors/thumb/nm0000188.jpg", "imdb_code": "0000188"}, {"name": "Tina Turner", "character_name": "Our Guests at Heartland", "imdb_code": "0877913"}, {"name": "Keith Carradine", "character_name": "Our Guests at Heartland", "url_small_image": "https://yts.mx/assets/images/actors/thumb/nm0001018.jpg", "imdb_code": "0001018"}], "torrents": [{"url": "https://yts.mx/torrent/download/C4B7426F69D7408C5AAAF9596EEA9CBD21508E5A", "hash": "C4B7426F69D7408C5AAAF9596EEA9CBD21508E5A", "quality": "720p", "type": "bluray", "seeds": 4, "peers": 3, "size": "1023.66 MB", "size_bytes": 1073385308, "date_uploaded": "2020-09-19 19:43:41", "date_uploaded_unix": 1600537421}, {"url": "https://yts.mx/torrent/download/D019EEAE10AF5C3C723A603809F6D6C0B546C48F", "hash": "D019EEAE10AF5C3C723A603809F6D6C0B546C48F", "quality": "1080p", "type": "bluray", "seeds": 5, "peers": 3, "size": "2.05 GB", "size_bytes": 2201170739, "date_uploaded": "2020-09-19 21:59:33", "date_uploaded_unix": 1600545573}], "date_uploaded": "2020-09-19 19:43:41", "date_uploaded_unix": 1600537421}}, "movie_suggestions": {"movie_count": 4, "movies": [{"id": 2704, "url": "https://yts.mx/movies/shaun-the-sheep-movie-2015", "imdb_code": "tt2872750", "title": "Shaun the Sheep Movie", "title_english": "Shaun the Sheep Movie", "title_long": "Shaun the Sheep Movie (2015)", "slug": "shaun-the-sheep-movie-2015", "year": 2015, "rating": 7.3, "runtime": 85, "genres": ["Action", "Adventure", "Animation", "Comedy", "Family", "Fantasy"], "summary": "Tired of working on the farm, the special sheep, Shaun, takes his flock and the farmer's dog, Bitzer, into his own \"temporary escape plan\" after an unexpected accident. Unfortunately, in the big city, the farmer is diagnosed with amnesia, that could possibly change their normal farm life forever, and the squad sets a plan in order to regain the farmer's memory and return to the farm. But, an animal control worker named Trumper intervenes in their plan.", "description_full": "Tired of working on the farm, the special sheep, Shaun, takes his flock and the farmer's dog, Bitzer, into his own \"temporary escape plan\" after an unexpected accident. Unfortunately, in the big city, the farmer is diagnosed with amnesia, that could possibly change their normal farm life forever, and the squad sets a plan in order to regain the farmer's memory and return to the farm. But, an animal control worker named Trumper intervenes in their plan.", "synopsis": "Tired of working on the farm, the special sheep, Shaun, takes his flock and the farmer's dog, Bitzer, into his own \"temporary escape plan\" after an unexpected accident. Unfortunately, in the big city, the farmer is diagnosed with amnesia, that could possibly change their normal farm life forever, and the squad sets a plan in order to regain the farmer's memory and return to the farm. But, an animal control worker named Trumper intervenes in their plan.", "yt_trailer_code": "E6qLSo9RsaE", "language": "en", "mpa_rating": "PG", "background_image": "https://yts.mx/assets/images/movies/shaun_the_sheep_movie_2015/background.jpg", "background_image_original": "https://yts.mx/assets/images/movies/shaun_the_sheep_movie_2015/background.jpg", "small_cover_image": "https://yts.mx/assets/images/movies/shaun_the_sheep_movie_2015/small-cover.jpg", "medium_cover_image": "https://yts.mx/assets/images/movies/shaun_the_sheep_movie_2015/medium-cover.jpg", "state": "ok", "torrents": [{"url": "https://yts.mx/torrent/download/CC3157CF0D4EE8020671F15DD8340009661E34DB", "hash": "CC3157CF0D4EE8020671F15DD8340009661E34DB", "quality": "720p", "seeds": 8, "peers": 0, "size": "701.76 MB", "size_bytes": 735848694, "date_uploaded": "2015-11-01 01:23:16", "date_uploaded_unix": 1446337396}, {"url": "https://yts.mx/torrent/download/B8B871BEDE279977AA5A5EAE80F2A17E5729424D", "hash": "B8B871BEDE279977AA5A5EAE80F2A17E5729424D", "quality": "1080p", "seeds": 24, "peers": 1, "size": "1.24 GB", "size_bytes": 1331439862, "date_uploaded": "2015-11-01 01:23:29", "date_uploaded_unix": 1446337409}], "date_uploaded": "2015-11-01 01:23:16", "date_uploaded_unix": 1446337396}, {"id": 4456, "url": "https://yts.mx/movies/paul-2011", "imdb_code": "tt1092026", "title": "Paul", "title_english": "Paul", "title_long": "Paul (2011)", "slug": "paul-2011", "year": 2011, "rating": 7, "runtime": 104, "genres": ["Action", "Adventure", "Animation", "Comedy", "Sci-Fi"], "summary": "Two sci-fi geeks take a pilgrimage to America's UFO heartland. While there, they accidentally meet an alien who brings them on an insane road trip that alters their universe forever. For the past 60 years, an alien named Paul (voiced by Seth Rogen) has been hanging out at a top-secret military base. When he discovers he's been taken prisoner, the space-traveling smart ass decides to escape the compound and hop on the first vehicle out of town - a rented RV containing Earthlings Graeme Willy (Simon Pegg) and Clive Gollings (Nick Frost). Chased by federal agents and the fanatical father of a young woman that they accidentally kidnap, Graeme and Clive hatch a fumbling escape plan to return Paul to his mother ship. And as two nerds struggle to help, one little green man might just take his fellow outcasts from misfits to intergalactic heroes.", "description_full": "Two sci-fi geeks take a pilgrimage to America's UFO heartland. While there, they accidentally meet an alien who brings them on an insane road trip that alters their universe forever. For the past 60 years, an alien named Paul (voiced by Seth Rogen) has been hanging out at a top-secret military base. When he discovers he's been taken prisoner, the space-traveling smart ass decides to escape the compound and hop on the first vehicle out of town - a rented RV containing Earthlings Graeme Willy (Simon Pegg) and Clive Gollings (Nick Frost). Chased by federal agents and the fanatical father of a young woman that they accidentally kidnap, Graeme and Clive hatch a fumbling escape plan to return Paul to his mother ship. And as two nerds struggle to help, one little green man might just take his fellow outcasts from misfits to intergalactic heroes.", "synopsis": "Two sci-fi geeks take a pilgrimage to America's UFO heartland. While there, they accidentally meet an alien who brings them on an insane road trip that alters their universe forever. For the past 60 years, an alien named Paul (voiced by Seth Rogen) has been hanging out at a top-secret military base. When he discovers he's been taken prisoner, the space-traveling smart ass decides to escape the compound and hop on the first vehicle out of town - a rented RV containing Earthlings Graeme Willy (Simon Pegg) and Clive Gollings (Nick Frost). Chased by federal agents and the fanatical father of a young woman that they accidentally kidnap, Graeme and Clive hatch a fumbling escape plan to return Paul to his mother ship. And as two nerds struggle to help, one little green man might just take his fellow outcasts from misfits to intergalactic heroes.", "yt_trailer_code": "tav42JTdW4A", "language": "en", "mpa_rating": "R", "background_image": "https://yts.mx/assets/images/movies/Paul_2011/background.jpg", "background_image_original": "https://yts.mx/assets/images/movies/Paul_2011/background.jpg", "small_cover_image": "https://yts.mx/assets/images/movies/Paul_2011/small-cover.jpg", "medium_cover_image": "https://yts.mx/assets/images/movies/Paul_2011/medium-cover.jpg", "state": "ok", "torrents": [{"url": "https://yts.mx/torrent/download/553A598AB3535ABA6E30FBD29015EACCEF7B9335", "hash": "553A598AB3535ABA6E30FBD29015EACCEF7B9335", "quality": "720p", "seeds": 22, "peers": 2, "size": "697.53 MB", "size_bytes": 731413217, "date_uploaded": "2015-11-08 02:41:01", "date_uploaded_unix": 1446946861}, {"url": "https://yts.mx/torrent/download/59270DEE22D3B4D568E87DE76C18C5B19507B838", "hash": "59270DEE22D3B4D568E87DE76C18C5B19507B838", "quality": "1080p", "seeds": 51, "peers": 7, "size": "1.74 GB", "size_bytes": 1868310774, "date_uploaded": "2018-10-27 04:10:45", "date_uploaded_unix": 1540606245}], "date_uploaded": "2015-11-08 02:41:01", "date_uploaded_unix": 1446946861}, {"id": 3400, "url": "https://yts.mx/movies/the-incredibles-2004", "imdb_code": "tt0317705", "title": "The Incredibles", "title_english": "The Incredibles", "title_long": "The Incredibles (2004)", "slug": "the-incredibles-2004", "year": 2004, "rating": 8, "runtime": 115, "genres": ["Action", "Adventure", "Animation", "Family"], "summary": "Bob Parr (A.K.A. Mr. Incredible), and his wife Helen (A.K.A. Elastigirl), are the world's greatest famous crime-fighting superheroes in Metroville. Always saving lives and battling evil on a daily basis. But fifteen years later, they have been forced to adopt civilian identities and retreat to the suburbs where they have no choice but to retire as superheroes to live a \"normal life\" with their three children Violet, Dash and Jack-Jack (who were secretly born with superpowers). Itching to get back into action, Bob gets his chance when a mysterious communication summons him to a remote island for a top secret assignment. He soon discovers that it will take a super family effort to rescue the world from total destruction.", "description_full": "Bob Parr (A.K.A. Mr. Incredible), and his wife Helen (A.K.A. Elastigirl), are the world's greatest famous crime-fighting superheroes in Metroville. Always saving lives and battling evil on a daily basis. But fifteen years later, they have been forced to adopt civilian identities and retreat to the suburbs where they have no choice but to retire as superheroes to live a \"normal life\" with their three children Violet, Dash and Jack-Jack (who were secretly born with superpowers). Itching to get back into action, Bob gets his chance when a mysterious communication summons him to a remote island for a top secret assignment. He soon discovers that it will take a super family effort to rescue the world from total destruction.", "synopsis": "Bob Parr (A.K.A. Mr. Incredible), and his wife Helen (A.K.A. Elastigirl), are the world's greatest famous crime-fighting superheroes in Metroville. Always saving lives and battling evil on a daily basis. But fifteen years later, they have been forced to adopt civilian identities and retreat to the suburbs where they have no choice but to retire as superheroes to live a \"normal life\" with their three children Violet, Dash and Jack-Jack (who were secretly born with superpowers). Itching to get back into action, Bob gets his chance when a mysterious communication summons him to a remote island for a top secret assignment. He soon discovers that it will take a super family effort to rescue the world from total destruction.", "yt_trailer_code": "6Uk7D3hILF4", "language": "en", "mpa_rating": "", "background_image": "https://yts.mx/assets/images/movies/The_Incredibles_2004/background.jpg", "background_image_original": "https://yts.mx/assets/images/movies/The_Incredibles_2004/background.jpg", "small_cover_image": "https://yts.mx/assets/images/movies/The_Incredibles_2004/small-cover.jpg", "medium_cover_image": "https://yts.mx/assets/images/movies/The_Incredibles_2004/medium-cover.jpg", "state": "ok", "torrents": [{"url": "https://yts.mx/torrent/download/0784728E0C4A38D76FEB5303AAB209226D690143", "hash": "0784728E0C4A38D76FEB5303AAB209226D690143", "quality": "720p", "seeds": 18, "peers": 14, "size": "699.86 MB", "size_bytes": 733856399, "date_uploaded": "2015-11-01 02:48:03", "date_uploaded_unix": 1446342483}, {"url": "https://yts.mx/torrent/download/9988B0F171FC23AAE15399ACF7518D956B759D07", "hash": "9988B0F171FC23AAE15399ACF7518D956B759D07", "quality": "1080p", "seeds": 259, "peers": 30, "size": "1.75 GB", "size_bytes": 1879048192, "date_uploaded": "2016-07-01 21:56:25", "date_uploaded_unix": 1467402985}], "date_uploaded": "2015-11-01 02:48:03", "date_uploaded_unix": 1446342483}, {"id": 8645, "url": "https://yts.mx/movies/ghost-mountaineer-2015", "imdb_code": "tt3199006", "title": "Ghost Mountaineer", "title_english": "Ghost Mountaineer", "title_long": "Ghost Mountaineer (2015)", "slug": "ghost-mountaineer-2015", "year": 2015, "rating": 6.1, "runtime": 0, "genres": ["Action", "Adventure", "Horror", "Mystery", "Thriller"], "summary": "Urmas Eero Liiv's feature film \"Must alpinist\" (Ghost Mountaineer) is a youth film with elements of horror which is based on real life events which took place during the Soviet era. It tells the story of an Soviet Estonian student hiking group which gets caught up in a series of scary events unfolding in wintry Siberia. The unpopular group leader Olle (Reimo Sagor), who becomes disappointed in his companions during the trip, disappears on the last day in the mountains. His rival, liberal-minded and adventurous Eero (Priit Pius) guides the descending hikers into a Buryate village on the mountain to seek help. A weird and insane chain of events is unleashed which seems to be orchestrated by the missing Olle. In a foreign land and among people they do not know, the hikers are faced with a task which they at first do not want to undertake and later are unable to tackle.", "description_full": "Urmas Eero Liiv's feature film \"Must alpinist\" (Ghost Mountaineer) is a youth film with elements of horror which is based on real life events which took place during the Soviet era. It tells the story of an Soviet Estonian student hiking group which gets caught up in a series of scary events unfolding in wintry Siberia. The unpopular group leader Olle (Reimo Sagor), who becomes disappointed in his companions during the trip, disappears on the last day in the mountains. His rival, liberal-minded and adventurous Eero (Priit Pius) guides the descending hikers into a Buryate village on the mountain to seek help. A weird and insane chain of events is unleashed which seems to be orchestrated by the missing Olle. In a foreign land and among people they do not know, the hikers are faced with a task which they at first do not want to undertake and later are unable to tackle.", "synopsis": "Urmas Eero Liiv's feature film \"Must alpinist\" (Ghost Mountaineer) is a youth film with elements of horror which is based on real life events which took place during the Soviet era. It tells the story of an Soviet Estonian student hiking group which gets caught up in a series of scary events unfolding in wintry Siberia. The unpopular group leader Olle (Reimo Sagor), who becomes disappointed in his companions during the trip, disappears on the last day in the mountains. His rival, liberal-minded and adventurous Eero (Priit Pius) guides the descending hikers into a Buryate village on the mountain to seek help. A weird and insane chain of events is unleashed which seems to be orchestrated by the missing Olle. In a foreign land and among people they do not know, the hikers are faced with a task which they at first do not want to undertake and later are unable to tackle.", "yt_trailer_code": "Pk2KXFxP1Do", "language": "et", "mpa_rating": "", "background_image": "https://yts.mx/assets/images/movies/ghost_mountaineer_2015/background.jpg", "background_image_original": "https://yts.mx/assets/images/movies/ghost_mountaineer_2015/background.jpg", "small_cover_image": "https://yts.mx/assets/images/movies/ghost_mountaineer_2015/small-cover.jpg", "medium_cover_image": "https://yts.mx/assets/images/movies/ghost_mountaineer_2015/medium-cover.jpg", "state": "ok", "torrents": [{"url": "https://yts.mx/torrent/download/4DA4485DCA8C76BF8CBE5A7B8AF73CFE4891B71B", "hash": "4DA4485DCA8C76BF8CBE5A7B8AF73CFE4891B71B", "quality": "720p", "seeds": 0, "peers": 0, "size": "837.71 MB", "size_bytes": 878402601, "date_uploaded": "2018-08-21 05:51:26", "date_uploaded_unix": 1534823486}, {"url": "https://yts.mx/torrent/download/BCB0E4BE5B17D9B9D0CEC63158FC83244F947C52", "hash": "BCB0E4BE5B17D9B9D0CEC63158FC83244F947C52", "quality": "1080p", "seeds": 4, "peers": 2, "size": "1.58 GB", "size_bytes": 1696512082, "date_uploaded": "2018-08-21 07:28:16", "date_uploaded_unix": 1534829296}], "date_uploaded": "2018-08-21 05:51:26", "date_uploaded_unix": 1534823486}]}}