{"movie_details": {"movie": {"id": 4450, "url": "https://yts.mx/movies/the-texas-chainsaw-massacre-2003", "imdb_code": "tt0324216", "title": "The Texas Chainsaw Massacre", "title_english": "The Texas Chainsaw Massacre", "title_long": "The Texas Chainsaw Massacre (2003)", "slug": "the-texas-chainsaw-massacre-2003", "year": 2003, "rating": 6.2, "runtime": 98, "genres": ["Action", "Crime", "Horror"], "download_count": 909, "like_count": 8, "description_intro": "Driving through the backwoods of Texas, five youths pick up a traumatized hitchhiker, who shoots herself in their van. Shaken by the suicide, the group seeks help from the locals, but their situation becomes even more surreal when they knock on the door of a remote homestead. It's quickly apparent the residents are a family of inbred psychopaths, and the unlucky youths suddenly find themselves running for their lives. In hot pursuit is a disfigured, chainsaw-wielding cannibal known as Leatherface.", "description_full": "Driving through the backwoods of Texas, five youths pick up a traumatized hitchhiker, who shoots herself in their van. Shaken by the suicide, the group seeks help from the locals, but their situation becomes even more surreal when they knock on the door of a remote homestead. It's quickly apparent the residents are a family of inbred psychopaths, and the unlucky youths suddenly find themselves running for their lives. In hot pursuit is a disfigured, chainsaw-wielding cannibal known as Leatherface.", "yt_trailer_code": "dg3LWY70rvw", "language": "en", "mpa_rating": "R", "background_image": "https://yts.mx/assets/images/movies/The_Texas_Chainsaw_Massacre_2003/background.jpg", "background_image_original": "https://yts.mx/assets/images/movies/The_Texas_Chainsaw_Massacre_2003/background.jpg", "small_cover_image": "https://yts.mx/assets/images/movies/The_Texas_Chainsaw_Massacre_2003/small-cover.jpg", "medium_cover_image": "https://yts.mx/assets/images/movies/The_Texas_Chainsaw_Massacre_2003/medium-cover.jpg", "large_cover_image": "https://yts.mx/assets/images/movies/The_Texas_Chainsaw_Massacre_2003/large-cover.jpg", "medium_screenshot_image1": "https://yts.mx/assets/images/movies/The_Texas_Chainsaw_Massacre_2003/medium-screenshot1.jpg", "medium_screenshot_image2": "https://yts.mx/assets/images/movies/The_Texas_Chainsaw_Massacre_2003/medium-screenshot2.jpg", "medium_screenshot_image3": "https://yts.mx/assets/images/movies/The_Texas_Chainsaw_Massacre_2003/medium-screenshot3.jpg", "large_screenshot_image1": "https://yts.mx/assets/images/movies/The_Texas_Chainsaw_Massacre_2003/large-screenshot1.jpg", "large_screenshot_image2": "https://yts.mx/assets/images/movies/The_Texas_Chainsaw_Massacre_2003/large-screenshot2.jpg", "large_screenshot_image3": "https://yts.mx/assets/images/movies/The_Texas_Chainsaw_Massacre_2003/large-screenshot3.jpg", "cast": [{"name": "Lauren German", "character_name": "Teenage Girl", "url_small_image": "https://yts.mx/assets/images/actors/thumb/nm0314514.jpg", "imdb_code": "0314514"}, {"name": "Jonathan Tucker", "character_name": "Morgan", "url_small_image": "https://yts.mx/assets/images/actors/thumb/nm0006958.jpg", "imdb_code": "0006958"}, {"name": "Eric Balfour", "character_name": "Kemper", "url_small_image": "https://yts.mx/assets/images/actors/thumb/nm0050156.jpg", "imdb_code": "0050156"}, {"name": "Mike Vogel", "character_name": "Andy", "url_small_image": "https://yts.mx/assets/images/actors/thumb/nm1036181.jpg", "imdb_code": "1036181"}], "torrents": [{"url": "https://yts.mx/torrent/download/FF19609717C97C187C150D5134222142DD26ED7D", "hash": "FF19609717C97C187C150D5134222142DD26ED7D", "quality": "720p", "type": "bluray", "seeds": 23, "peers": 4, "size": "650.28 MB", "size_bytes": 681868001, "date_uploaded": "2015-11-08 02:26:26", "date_uploaded_unix": 1446945986}, {"url": "https://yts.mx/torrent/download/F87E56BBC6E81F4F7896D1529ADDF65A744AC143", "hash": "F87E56BBC6E81F4F7896D1529ADDF65A744AC143", "quality": "1080p", "type": "bluray", "seeds": 6, "peers": 0, "size": "1.40 GB", "size_bytes": 1503238554, "date_uploaded": "2015-11-08 02:26:26", "date_uploaded_unix": 1446945986}], "date_uploaded": "2015-11-08 02:26:26", "date_uploaded_unix": 1446945986}}, "movie_suggestions": {"movie_count": 4, "movies": [{"id": 23393, "url": "https://yts.mx/movies/an-american-haunting-2005", "imdb_code": "tt0429573", "title": "An American Haunting", "title_english": "An American Haunting", "title_long": "An American Haunting (2005)", "slug": "an-american-haunting-2005", "year": 2005, "rating": 5.1, "runtime": 83, "genres": ["Action", "Drama", "History", "Horror", "Mystery", "Thriller"], "summary": "In 2006, in Red River, Tennessee, a teenager has frequent nightmares. Her mother reads an old letter from 1817", "description_full": "In 2006, in Red River, Tennessee, a teenager has frequent nightmares. Her mother reads an old letter from 1817", "synopsis": "In 2006, in Red River, Tennessee, a teenager has frequent nightmares. Her mother reads an old letter from 1817", "yt_trailer_code": "8Mr1wMiihKI", "language": "en", "mpa_rating": "PG-13", "background_image": "https://yts.mx/assets/images/movies/an_american_haunting_2005/background.jpg", "background_image_original": "https://yts.mx/assets/images/movies/an_american_haunting_2005/background.jpg", "small_cover_image": "https://yts.mx/assets/images/movies/an_american_haunting_2005/small-cover.jpg", "medium_cover_image": "https://yts.mx/assets/images/movies/an_american_haunting_2005/medium-cover.jpg", "state": "ok", "torrents": [{"url": "https://yts.mx/torrent/download/9D2132838B39C9C5CED7B97E6E3669F68D681B0B", "hash": "9D2132838B39C9C5CED7B97E6E3669F68D681B0B", "quality": "720p", "seeds": 5, "peers": 0, "size": "829.34 MB", "size_bytes": 869626020, "date_uploaded": "2020-11-09 13:50:53", "date_uploaded_unix": 1604926253}, {"url": "https://yts.mx/torrent/download/F51074BEC33A5C1887A76A371E7160B71DBFFBE7", "hash": "F51074BEC33A5C1887A76A371E7160B71DBFFBE7", "quality": "1080p", "seeds": 9, "peers": 2, "size": "1.66 GB", "size_bytes": 1782411428, "date_uploaded": "2020-11-09 15:21:21", "date_uploaded_unix": 1604931681}], "date_uploaded": "2020-11-09 13:50:53", "date_uploaded_unix": 1604926253}, {"id": 12084, "url": "https://yts.mx/movies/coffee-and-cigarettes-2003", "imdb_code": "tt0379217", "title": "Coffee and Cigarettes", "title_english": "Coffee and Cigarettes", "title_long": "Coffee and Cigarettes (2003)", "slug": "coffee-and-cigarettes-2003", "year": 2003, "rating": 7.1, "runtime": 95, "genres": ["Action", "Comedy", "Drama", "Music"], "summary": "Eleven separate vignettes are presented. In each, celebrities, playing semi-fictionalized versions of themselves (with the exception of the characters of various wait staff, and one actor playing a lookalike cousin of herself), meet in a food service establishment with coffee/tea and cigarettes involved. Beyond the topic of discussion that brought them together, they often talk directly about coffee and cigarettes, more often that coffee and cigarettes, and by association caffeine and nicotine, are not healthy, especially if they are the only things constituting lunch. Other recurring themes include the Lee family, cousinhood, celebrity worship, the connection between the medical and musical careers, and Nikola Tesla's belief that the Earth is a conductor of acoustic resonance. In all cases, the coming together for coffee/tea and smokes acts as a bridge to overcome disagreements, and/or makes uncomfortable situations less uncomfortable.", "description_full": "Eleven separate vignettes are presented. In each, celebrities, playing semi-fictionalized versions of themselves (with the exception of the characters of various wait staff, and one actor playing a lookalike cousin of herself), meet in a food service establishment with coffee/tea and cigarettes involved. Beyond the topic of discussion that brought them together, they often talk directly about coffee and cigarettes, more often that coffee and cigarettes, and by association caffeine and nicotine, are not healthy, especially if they are the only things constituting lunch. Other recurring themes include the Lee family, cousinhood, celebrity worship, the connection between the medical and musical careers, and Nikola Tesla's belief that the Earth is a conductor of acoustic resonance. In all cases, the coming together for coffee/tea and smokes acts as a bridge to overcome disagreements, and/or makes uncomfortable situations less uncomfortable.", "synopsis": "Eleven separate vignettes are presented. In each, celebrities, playing semi-fictionalized versions of themselves (with the exception of the characters of various wait staff, and one actor playing a lookalike cousin of herself), meet in a food service establishment with coffee/tea and cigarettes involved. Beyond the topic of discussion that brought them together, they often talk directly about coffee and cigarettes, more often that coffee and cigarettes, and by association caffeine and nicotine, are not healthy, especially if they are the only things constituting lunch. Other recurring themes include the Lee family, cousinhood, celebrity worship, the connection between the medical and musical careers, and Nikola Tesla's belief that the Earth is a conductor of acoustic resonance. In all cases, the coming together for coffee/tea and smokes acts as a bridge to overcome disagreements, and/or makes uncomfortable situations less uncomfortable.", "yt_trailer_code": "mM6Mpn0-eyQ", "language": "en", "mpa_rating": "R", "background_image": "https://yts.mx/assets/images/movies/coffee_and_cigarettes_2003/background.jpg", "background_image_original": "https://yts.mx/assets/images/movies/coffee_and_cigarettes_2003/background.jpg", "small_cover_image": "https://yts.mx/assets/images/movies/coffee_and_cigarettes_2003/small-cover.jpg", "medium_cover_image": "https://yts.mx/assets/images/movies/coffee_and_cigarettes_2003/medium-cover.jpg", "state": "ok", "torrents": [{"url": "https://yts.mx/torrent/download/1A218734BAECD2B2B6D00BA3C7817D0C7E6CFA3D", "hash": "1A218734BAECD2B2B6D00BA3C7817D0C7E6CFA3D", "quality": "720p", "seeds": 12, "peers": 2, "size": "818.49 MB", "size_bytes": 858248970, "date_uploaded": "2019-05-22 04:06:37", "date_uploaded_unix": 1558490797}, {"url": "https://yts.mx/torrent/download/EB6258B45FC604943E750BE688AC5530243B75A3", "hash": "EB6258B45FC604943E750BE688AC5530243B75A3", "quality": "1080p", "seeds": 26, "peers": 3, "size": "1.54 GB", "size_bytes": 1653562409, "date_uploaded": "2019-05-22 06:18:07", "date_uploaded_unix": 1558498687}], "date_uploaded": "2019-05-22 04:06:37", "date_uploaded_unix": 1558490797}, {"id": 23536, "url": "https://yts.mx/movies/the-patriots-1994", "imdb_code": "tt0110796", "title": "The Patriots", "title_english": "The Patriots", "title_long": "The Patriots (1994)", "slug": "the-patriots-1994", "year": 1994, "rating": 7.3, "runtime": 138, "genres": ["Action", "Thriller"], "summary": "At 18, Ariel Brenner leaves Paris and his family to live in Israel. He secretly joins the Mossad, the Isreali secret service. After years of training, his first mission is in Paris to steal secrets from Remy Prieur, a French atomic scientist... We will assist to the methods, the manipulations, the abuses, the machiavellism, the doubts of secret agents.", "description_full": "At 18, Ariel Brenner leaves Paris and his family to live in Israel. He secretly joins the Mossad, the Isreali secret service. After years of training, his first mission is in Paris to steal secrets from Remy Prieur, a French atomic scientist... We will assist to the methods, the manipulations, the abuses, the machiavellism, the doubts of secret agents.", "synopsis": "At 18, Ariel Brenner leaves Paris and his family to live in Israel. He secretly joins the Mossad, the Isreali secret service. After years of training, his first mission is in Paris to steal secrets from Remy Prieur, a French atomic scientist... We will assist to the methods, the manipulations, the abuses, the machiavellism, the doubts of secret agents.", "yt_trailer_code": "", "language": "fr", "mpa_rating": "", "background_image": "https://yts.mx/assets/images/movies/the_patriots_1994/background.jpg", "background_image_original": "https://yts.mx/assets/images/movies/the_patriots_1994/background.jpg", "small_cover_image": "https://yts.mx/assets/images/movies/the_patriots_1994/small-cover.jpg", "medium_cover_image": "https://yts.mx/assets/images/movies/the_patriots_1994/medium-cover.jpg", "state": "ok", "torrents": [{"url": "https://yts.mx/torrent/download/37CE3232CCC8AA24FAE2DC54FCD7B54B6E201172", "hash": "37CE3232CCC8AA24FAE2DC54FCD7B54B6E201172", "quality": "720p", "seeds": 8, "peers": 1, "size": "1.31 GB", "size_bytes": 1406601789, "date_uploaded": "2020-11-14 02:17:28", "date_uploaded_unix": 1605316648}, {"url": "https://yts.mx/torrent/download/4A3346A184356FB30E7CBC0C7CE84F6C24D3D4EA", "hash": "4A3346A184356FB30E7CBC0C7CE84F6C24D3D4EA", "quality": "1080p", "seeds": 5, "peers": 1, "size": "2.69 GB", "size_bytes": 2888365507, "date_uploaded": "2020-11-14 05:21:15", "date_uploaded_unix": 1605327675}], "date_uploaded": "2020-11-14 02:17:28", "date_uploaded_unix": 1605316648}, {"id": 10498, "url": "https://yts.mx/movies/baaghi-2016", "imdb_code": "tt4864932", "title": "Baaghi", "title_english": "Baaghi", "title_long": "Baaghi (2016)", "slug": "baaghi-2016", "year": 2016, "rating": 5.2, "runtime": 133, "genres": ["Action", "Romance", "Thriller"], "summary": "A martial arts student seeks revenge after the murder of his master.", "description_full": "A martial arts student seeks revenge after the murder of his master.", "synopsis": "A martial arts student seeks revenge after the murder of his master.", "yt_trailer_code": "8HQIKJBUsQk", "language": "hi", "mpa_rating": "", "background_image": "https://yts.mx/assets/images/movies/baaghi_2016/background.jpg", "background_image_original": "https://yts.mx/assets/images/movies/baaghi_2016/background.jpg", "small_cover_image": "https://yts.mx/assets/images/movies/baaghi_2016/small-cover.jpg", "medium_cover_image": "https://yts.mx/assets/images/movies/baaghi_2016/medium-cover.jpg", "state": "ok", "torrents": [{"url": "https://yts.mx/torrent/download/669EBAB3E3C06F74CFCC0A7CBFA58F90B76F5889", "hash": "669EBAB3E3C06F74CFCC0A7CBFA58F90B76F5889", "quality": "720p", "seeds": 21, "peers": 5, "size": "1.14 GB", "size_bytes": 1224065679, "date_uploaded": "2019-01-12 17:55:05", "date_uploaded_unix": 1547312105}, {"url": "https://yts.mx/torrent/download/0883B2A60CA5BCBEE424BDBFBD143EA52068777C", "hash": "0883B2A60CA5BCBEE424BDBFBD143EA52068777C", "quality": "1080p", "seeds": 12, "peers": 1, "size": "2.17 GB", "size_bytes": 2330019758, "date_uploaded": "2019-01-12 19:58:40", "date_uploaded_unix": 1547319520}], "date_uploaded": "2019-01-12 17:55:05", "date_uploaded_unix": 1547312105}]}}