{"movie_details": {"movie": {"id": 8017, "url": "https://yts.mx/movies/cold-november-2017", "imdb_code": "tt4712516", "title": "Cold November", "title_english": "Cold November", "title_long": "Cold November (2017)", "slug": "cold-november-2017", "year": 2017, "rating": 4.5, "runtime": 91, "genres": ["Drama", "Family", "Thriller"], "download_count": 27977, "like_count": 7, "description_intro": "A 12-year-old girl being raised within a matriarchal household is taken through the right of passage of killing a deer for the first time. Expectations dissolve into chaos, and Florence finds herself alone, relying on instinct and training to follow through with her decisions, pull herself together, and face becoming an adult in the North American wilderness.", "description_full": "A 12-year-old girl being raised within a matriarchal household is taken through the right of passage of killing a deer for the first time. Expectations dissolve into chaos, and Florence finds herself alone, relying on instinct and training to follow through with her decisions, pull herself together, and face becoming an adult in the North American wilderness.", "yt_trailer_code": "hs7YeTuxjU0", "language": "en", "mpa_rating": "", "background_image": "https://yts.mx/assets/images/movies/cold_november_2017/background.jpg", "background_image_original": "https://yts.mx/assets/images/movies/cold_november_2017/background.jpg", "small_cover_image": "https://yts.mx/assets/images/movies/cold_november_2017/small-cover.jpg", "medium_cover_image": "https://yts.mx/assets/images/movies/cold_november_2017/medium-cover.jpg", "large_cover_image": "https://yts.mx/assets/images/movies/cold_november_2017/large-cover.jpg", "medium_screenshot_image1": "https://yts.mx/assets/images/movies/cold_november_2017/medium-screenshot1.jpg", "medium_screenshot_image2": "https://yts.mx/assets/images/movies/cold_november_2017/medium-screenshot2.jpg", "medium_screenshot_image3": "https://yts.mx/assets/images/movies/cold_november_2017/medium-screenshot3.jpg", "large_screenshot_image1": "https://yts.mx/assets/images/movies/cold_november_2017/large-screenshot1.jpg", "large_screenshot_image2": "https://yts.mx/assets/images/movies/cold_november_2017/large-screenshot2.jpg", "large_screenshot_image3": "https://yts.mx/assets/images/movies/cold_november_2017/large-screenshot3.jpg", "torrents": [{"url": "https://yts.mx/torrent/download/F6BA9ED185412D118DE0325B8CF37F1F7532326A", "hash": "F6BA9ED185412D118DE0325B8CF37F1F7532326A", "quality": "720p", "type": "web", "seeds": 0, "peers": 1, "size": "774.02 MB", "size_bytes": 811618796, "date_uploaded": "2018-06-13 04:13:15", "date_uploaded_unix": 1528855995}, {"url": "https://yts.mx/torrent/download/9B61F6F4143335140710EAB1DD3B0FC3BEA6D39A", "hash": "9B61F6F4143335140710EAB1DD3B0FC3BEA6D39A", "quality": "1080p", "type": "web", "seeds": 0, "peers": 2, "size": "1.46 GB", "size_bytes": 1567663063, "date_uploaded": "2018-06-13 05:51:19", "date_uploaded_unix": 1528861879}], "date_uploaded": "2018-06-13 04:13:15", "date_uploaded_unix": 1528855995}}, "movie_suggestions": {"movie_count": 4, "movies": [{"id": 12954, "url": "https://yts.mx/movies/not-reconciled-1965", "imdb_code": "tt0059503", "title": "Not Reconciled", "title_english": "Not Reconciled", "title_long": "Not Reconciled (1965)", "slug": "not-reconciled-1965", "year": 1965, "rating": 6.4, "runtime": 55, "genres": ["Action", "Drama", "History"], "summary": "An entangled story which details the lives of a German family throughout their various generations.", "description_full": "An entangled story which details the lives of a German family throughout their various generations.", "synopsis": "An entangled story which details the lives of a German family throughout their various generations.", "yt_trailer_code": "", "language": "de", "mpa_rating": "", "background_image": "https://yts.mx/assets/images/movies/not_reconciled_1965/background.jpg", "background_image_original": "https://yts.mx/assets/images/movies/not_reconciled_1965/background.jpg", "small_cover_image": "https://yts.mx/assets/images/movies/not_reconciled_1965/small-cover.jpg", "medium_cover_image": "https://yts.mx/assets/images/movies/not_reconciled_1965/medium-cover.jpg", "state": "ok", "torrents": [{"url": "https://yts.mx/torrent/download/E540E19F74201A6758D161F671B2D31E43DF0248", "hash": "E540E19F74201A6758D161F671B2D31E43DF0248", "quality": "720p", "seeds": 0, "peers": 0, "size": "430.46 MB", "size_bytes": 451370025, "date_uploaded": "2019-07-19 03:46:29", "date_uploaded_unix": 1563500789}, {"url": "https://yts.mx/torrent/download/3517D7591636622C650501615BCC1BFAA75ED5D5", "hash": "3517D7591636622C650501615BCC1BFAA75ED5D5", "quality": "1080p", "seeds": 2, "peers": 3, "size": "843.98 MB", "size_bytes": 884977172, "date_uploaded": "2019-07-19 04:37:24", "date_uploaded_unix": 1563503844}], "date_uploaded": "2019-07-19 03:46:29", "date_uploaded_unix": 1563500789}, {"id": 12065, "url": "https://yts.mx/movies/johnny-come-lately-1943", "imdb_code": "tt0036057", "title": "Johnny Come Lately", "title_english": "Johnny Come Lately", "title_long": "Johnny Come Lately (1943)", "slug": "johnny-come-lately-1943", "year": 1943, "rating": 6.8, "runtime": 97, "genres": ["Action", "Drama"], "summary": "Newspaper man wanders about and helps older woman save her paper.", "description_full": "Newspaper man wanders about and helps older woman save her paper.", "synopsis": "Newspaper man wanders about and helps older woman save her paper.", "yt_trailer_code": "", "language": "en", "mpa_rating": "", "background_image": "https://yts.mx/assets/images/movies/johnny_come_lately_1943/background.jpg", "background_image_original": "https://yts.mx/assets/images/movies/johnny_come_lately_1943/background.jpg", "small_cover_image": "https://yts.mx/assets/images/movies/johnny_come_lately_1943/small-cover.jpg", "medium_cover_image": "https://yts.mx/assets/images/movies/johnny_come_lately_1943/medium-cover.jpg", "state": "ok", "torrents": [{"url": "https://yts.mx/torrent/download/B1E51DE49FE0E6313BA7A605B82FA265669634FA", "hash": "B1E51DE49FE0E6313BA7A605B82FA265669634FA", "quality": "720p", "seeds": 4, "peers": 1, "size": "810.02 MB", "size_bytes": 849367532, "date_uploaded": "2019-05-20 17:33:42", "date_uploaded_unix": 1558366422}, {"url": "https://yts.mx/torrent/download/4758633C479B7EA28EF4E62D8A41EA09E53FBF8F", "hash": "4758633C479B7EA28EF4E62D8A41EA09E53FBF8F", "quality": "1080p", "seeds": 0, "peers": 2, "size": "1.54 GB", "size_bytes": 1653562409, "date_uploaded": "2019-05-20 19:12:29", "date_uploaded_unix": 1558372349}], "date_uploaded": "2019-05-20 17:33:42", "date_uploaded_unix": 1558366422}, {"id": 13724, "url": "https://yts.mx/movies/wild-horses-2015", "imdb_code": "tt4442130", "title": "Wild Horses", "title_english": "Wild Horses", "title_long": "Wild Horses (2015)", "slug": "wild-horses-2015", "year": 2015, "rating": 4.8, "runtime": 100, "genres": ["Crime", "Drama", "Western"], "summary": "A detective opens up a fifteen-year-old missing persons case, and begins to suspect that the missing boy was murdered, and that a local rancher was involved.", "description_full": "A detective opens up a fifteen-year-old missing persons case, and begins to suspect that the missing boy was murdered, and that a local rancher was involved.", "synopsis": "A detective opens up a fifteen-year-old missing persons case, and begins to suspect that the missing boy was murdered, and that a local rancher was involved.", "yt_trailer_code": "bhaiC3_p8go", "language": "en", "mpa_rating": "R", "background_image": "https://yts.mx/assets/images/movies/wild_horses_2015/background.jpg", "background_image_original": "https://yts.mx/assets/images/movies/wild_horses_2015/background.jpg", "small_cover_image": "https://yts.mx/assets/images/movies/wild_horses_2015/small-cover.jpg", "medium_cover_image": "https://yts.mx/assets/images/movies/wild_horses_2015/medium-cover.jpg", "state": "ok", "torrents": [{"url": "https://yts.mx/torrent/download/241AD353973C984F8A35A68295F957EECA903FAE", "hash": "241AD353973C984F8A35A68295F957EECA903FAE", "quality": "720p", "seeds": 5, "peers": 2, "size": "912.19 MB", "size_bytes": 956500541, "date_uploaded": "2019-09-26 10:05:54", "date_uploaded_unix": 1569485154}, {"url": "https://yts.mx/torrent/download/D16BA94818DF2C7D49BA4635A853ED2AE01C94E8", "hash": "D16BA94818DF2C7D49BA4635A853ED2AE01C94E8", "quality": "1080p", "seeds": 4, "peers": 0, "size": "1.61 GB", "size_bytes": 1728724337, "date_uploaded": "2019-09-26 11:50:38", "date_uploaded_unix": 1569491438}], "date_uploaded": "2019-09-26 10:05:54", "date_uploaded_unix": 1569485154}, {"id": 11407, "url": "https://yts.mx/movies/a-dandy-in-aspic-1968", "imdb_code": "tt0062859", "title": "A Dandy in Aspic", "title_english": "A Dandy in Aspic", "title_long": "A Dandy in Aspic (1968)", "slug": "a-dandy-in-aspic-1968", "year": 1968, "rating": 6.2, "runtime": 107, "genres": ["Action", "Drama", "Thriller"], "summary": "Double-Agent Alexander Eberlin (Laurence Harvey) is assigned by the British to hunt out a Russian spy, known to them as Krasnevin. Only Eberlin knows that Krasnevin is none other than himself. Accompanying him on his mission is a ruthless partner, who gradually discovers his secret as Eberlin tries to maneuver himself out of a desperate situation.", "description_full": "Double-Agent Alexander Eberlin (Laurence Harvey) is assigned by the British to hunt out a Russian spy, known to them as Krasnevin. Only Eberlin knows that Krasnevin is none other than himself. Accompanying him on his mission is a ruthless partner, who gradually discovers his secret as Eberlin tries to maneuver himself out of a desperate situation.", "synopsis": "Double-Agent Alexander Eberlin (Laurence Harvey) is assigned by the British to hunt out a Russian spy, known to them as Krasnevin. Only Eberlin knows that Krasnevin is none other than himself. Accompanying him on his mission is a ruthless partner, who gradually discovers his secret as Eberlin tries to maneuver himself out of a desperate situation.", "yt_trailer_code": "", "language": "en", "mpa_rating": "", "background_image": "https://yts.mx/assets/images/movies/a_dandy_in_aspic_1968/background.jpg", "background_image_original": "https://yts.mx/assets/images/movies/a_dandy_in_aspic_1968/background.jpg", "small_cover_image": "https://yts.mx/assets/images/movies/a_dandy_in_aspic_1968/small-cover.jpg", "medium_cover_image": "https://yts.mx/assets/images/movies/a_dandy_in_aspic_1968/medium-cover.jpg", "state": "ok", "torrents": [{"url": "https://yts.mx/torrent/download/214B8F4F84C52A63C0281038458D4131EF277B62", "hash": "214B8F4F84C52A63C0281038458D4131EF277B62", "quality": "720p", "seeds": 0, "peers": 3, "size": "899.24 MB", "size_bytes": 942921482, "date_uploaded": "2019-04-01 20:02:29", "date_uploaded_unix": 1554141749}, {"url": "https://yts.mx/torrent/download/101313F504518F4EE0E67A0360B0AD6788E10CFF", "hash": "101313F504518F4EE0E67A0360B0AD6788E10CFF", "quality": "1080p", "seeds": 2, "peers": 1, "size": "1.7 GB", "size_bytes": 1825361101, "date_uploaded": "2019-04-01 22:10:05", "date_uploaded_unix": 1554149405}], "date_uploaded": "2019-04-01 20:02:29", "date_uploaded_unix": 1554141749}]}}