{"movie_details": {"movie": {"id": 9340, "url": "https://yts.mx/movies/the-spy-who-dumped-me-2018", "imdb_code": "tt6663582", "title": "The Spy Who Dumped Me", "title_english": "The Spy Who Dumped Me", "title_long": "The Spy Who Dumped Me (2018)", "slug": "the-spy-who-dumped-me-2018", "year": 2018, "rating": 6, "runtime": 117, "genres": ["Action", "Adventure", "Comedy"], "download_count": 1226039, "like_count": 199, "description_intro": "Audrey (Mila Kunis) and Morgan (Kate McKinnon), two thirty-year-old best friends in Los Angeles, are thrust unexpectedly into an international conspiracy when Audrey's ex-boyfriend shows up at their apartment with a team of deadly assassins on his trail. Surprising even themselves, the duo jump into action, on the run throughout Europe from assassins and a suspicious-but-charming British agent, as they hatch a plan to save the world.", "description_full": "Audrey (Mila Kunis) and Morgan (Kate McKinnon), two thirty-year-old best friends in Los Angeles, are thrust unexpectedly into an international conspiracy when Audrey's ex-boyfriend shows up at their apartment with a team of deadly assassins on his trail. Surprising even themselves, the duo jump into action, on the run throughout Europe from assassins and a suspicious-but-charming British agent, as they hatch a plan to save the world.", "yt_trailer_code": "OZsYiWBgFOk", "language": "en", "mpa_rating": "R", "background_image": "https://yts.mx/assets/images/movies/the_spy_who_dumped_me_2018/background.jpg", "background_image_original": "https://yts.mx/assets/images/movies/the_spy_who_dumped_me_2018/background.jpg", "small_cover_image": "https://yts.mx/assets/images/movies/the_spy_who_dumped_me_2018/small-cover.jpg", "medium_cover_image": "https://yts.mx/assets/images/movies/the_spy_who_dumped_me_2018/medium-cover.jpg", "large_cover_image": "https://yts.mx/assets/images/movies/the_spy_who_dumped_me_2018/large-cover.jpg", "medium_screenshot_image1": "https://yts.mx/assets/images/movies/the_spy_who_dumped_me_2018/medium-screenshot1.jpg", "medium_screenshot_image2": "https://yts.mx/assets/images/movies/the_spy_who_dumped_me_2018/medium-screenshot2.jpg", "medium_screenshot_image3": "https://yts.mx/assets/images/movies/the_spy_who_dumped_me_2018/medium-screenshot3.jpg", "large_screenshot_image1": "https://yts.mx/assets/images/movies/the_spy_who_dumped_me_2018/large-screenshot1.jpg", "large_screenshot_image2": "https://yts.mx/assets/images/movies/the_spy_who_dumped_me_2018/large-screenshot2.jpg", "large_screenshot_image3": "https://yts.mx/assets/images/movies/the_spy_who_dumped_me_2018/large-screenshot3.jpg", "cast": [{"name": "Fred Melamed", "character_name": "Roger", "url_small_image": "https://yts.mx/assets/images/actors/thumb/nm0577329.jpg", "imdb_code": "0577329"}, {"name": "Mila Kunis", "character_name": "Audrey", "url_small_image": "https://yts.mx/assets/images/actors/thumb/nm0005109.jpg", "imdb_code": "0005109"}, {"name": "Justin Theroux", "character_name": "Drew", "url_small_image": "https://yts.mx/assets/images/actors/thumb/nm0857620.jpg", "imdb_code": "0857620"}, {"name": "Kate McKinnon", "character_name": "Morgan", "imdb_code": "0571952"}], "torrents": [{"url": "https://yts.mx/torrent/download/280E7869832D8121A057298F3185B0A942F06038", "hash": "280E7869832D8121A057298F3185B0A942F06038", "quality": "720p", "type": "bluray", "seeds": 106, "peers": 7, "size": "995.33 MB", "size_bytes": 1043679150, "date_uploaded": "2018-10-18 16:17:22", "date_uploaded_unix": 1539872242}, {"url": "https://yts.mx/torrent/download/BDB75809F75D9C4ABE15FF67BC13F4AD6C4B529F", "hash": "BDB75809F75D9C4ABE15FF67BC13F4AD6C4B529F", "quality": "1080p", "type": "bluray", "seeds": 80, "peers": 4, "size": "1.87 GB", "size_bytes": 2007897211, "date_uploaded": "2018-10-18 18:28:02", "date_uploaded_unix": 1539880082}, {"url": "https://yts.mx/torrent/download/89906B01C0953725551C63EED52F3181288DDDDD", "hash": "89906B01C0953725551C63EED52F3181288DDDDD", "quality": "720p", "type": "web", "seeds": 39, "peers": 2, "size": "989.98 MB", "size_bytes": 1038069268, "date_uploaded": "2018-10-16 15:52:53", "date_uploaded_unix": 1539697973}, {"url": "https://yts.mx/torrent/download/FF1D958C4CC5472E36CF7EBD209612617D12EB7F", "hash": "FF1D958C4CC5472E36CF7EBD209612617D12EB7F", "quality": "1080p", "type": "web", "seeds": 29, "peers": 5, "size": "1.86 GB", "size_bytes": 1997159793, "date_uploaded": "2018-10-16 17:57:42", "date_uploaded_unix": 1539705462}], "date_uploaded": "2018-10-16 15:52:53", "date_uploaded_unix": 1539697973}}, "movie_suggestions": {"movie_count": 4, "movies": [{"id": 6209, "url": "https://yts.mx/movies/i-am-bolt-2016", "imdb_code": "tt4647900", "title": "I Am Bolt", "title_english": "I Am Bolt", "title_long": "I Am Bolt (2016)", "slug": "i-am-bolt-2016", "year": 2016, "rating": 7.1, "runtime": 107, "genres": ["Action", "Biography", "Documentary", "Sport"], "summary": "The legacy of the fastest man in history, Usain Bolt.", "description_full": "The legacy of the fastest man in history, Usain Bolt.", "synopsis": "The legacy of the fastest man in history, Usain Bolt.", "yt_trailer_code": "XVje1n8K240", "language": "en", "mpa_rating": "PG", "background_image": "https://yts.mx/assets/images/movies/i_am_bolt_2016/background.jpg", "background_image_original": "https://yts.mx/assets/images/movies/i_am_bolt_2016/background.jpg", "small_cover_image": "https://yts.mx/assets/images/movies/i_am_bolt_2016/small-cover.jpg", "medium_cover_image": "https://yts.mx/assets/images/movies/i_am_bolt_2016/medium-cover.jpg", "state": "ok", "torrents": [{"url": "https://yts.mx/torrent/download/4CCEF1F7856C749257A711946DE4C8AC52428B3C", "hash": "4CCEF1F7856C749257A711946DE4C8AC52428B3C", "quality": "720p", "seeds": 21, "peers": 4, "size": "808.51 MB", "size_bytes": 847784182, "date_uploaded": "2016-12-03 15:23:17", "date_uploaded_unix": 1480774997}, {"url": "https://yts.mx/torrent/download/453B31AE3081820D80F6387074EB1CFF4615D9F1", "hash": "453B31AE3081820D80F6387074EB1CFF4615D9F1", "quality": "1080p", "seeds": 19, "peers": 5, "size": "1.68 GB", "size_bytes": 1803886264, "date_uploaded": "2016-12-03 19:20:16", "date_uploaded_unix": 1480789216}], "date_uploaded": "2016-12-03 15:23:17", "date_uploaded_unix": 1480774997}, {"id": 15574, "url": "https://yts.mx/movies/the-corrupted-2019", "imdb_code": "tt5687270", "title": "The Corrupted", "title_english": "The Corrupted", "title_long": "The Corrupted (2019)", "slug": "the-corrupted-2019", "year": 2019, "rating": 5.6, "runtime": 103, "genres": ["Action", "Crime", "Drama", "Thriller"], "summary": "Set after the 2012 London Olympics, the film follows Liam (Sam Claflin), an ex-con trying to win back the love and trust of his family. He has lost everything at the hands of a local crime syndicate run by Clifford Cullen (Spall), who has high-level connections in politics, finance and the police force. Liam's drive for redemption sees him caught up in a web of conspiracy, crime, and corruption.", "description_full": "Set after the 2012 London Olympics, the film follows Liam (Sam Claflin), an ex-con trying to win back the love and trust of his family. He has lost everything at the hands of a local crime syndicate run by Clifford Cullen (Spall), who has high-level connections in politics, finance and the police force. Liam's drive for redemption sees him caught up in a web of conspiracy, crime, and corruption.", "synopsis": "Set after the 2012 London Olympics, the film follows Liam (Sam Claflin), an ex-con trying to win back the love and trust of his family. He has lost everything at the hands of a local crime syndicate run by Clifford Cullen (Spall), who has high-level connections in politics, finance and the police force. Liam's drive for redemption sees him caught up in a web of conspiracy, crime, and corruption.", "yt_trailer_code": "6lDcA_aGPh8", "language": "en", "mpa_rating": "R", "background_image": "https://yts.mx/assets/images/movies/the_corrupted_2019/background.jpg", "background_image_original": "https://yts.mx/assets/images/movies/the_corrupted_2019/background.jpg", "small_cover_image": "https://yts.mx/assets/images/movies/the_corrupted_2019/small-cover.jpg", "medium_cover_image": "https://yts.mx/assets/images/movies/the_corrupted_2019/medium-cover.jpg", "state": "ok", "torrents": [{"url": "https://yts.mx/torrent/download/A0A4746578B4ACDAF1B4EB6A57B39FEADAD6D020", "hash": "A0A4746578B4ACDAF1B4EB6A57B39FEADAD6D020", "quality": "720p", "seeds": 12, "peers": 3, "size": "951.95 MB", "size_bytes": 998191923, "date_uploaded": "2020-02-24 23:19:13", "date_uploaded_unix": 1582582753}, {"url": "https://yts.mx/torrent/download/8487C5E782B01CF61F416D962E64C699CA3A17DC", "hash": "8487C5E782B01CF61F416D962E64C699CA3A17DC", "quality": "1080p", "seeds": 12, "peers": 4, "size": "1.84 GB", "size_bytes": 1975684956, "date_uploaded": "2020-02-25 01:07:32", "date_uploaded_unix": 1582589252}], "date_uploaded": "2020-02-24 23:19:13", "date_uploaded_unix": 1582582753}, {"id": 6793, "url": "https://yts.mx/movies/6-days-2017", "imdb_code": "tt4703048", "title": "6 Days", "title_english": "6 Days", "title_long": "6 Days (2017)", "slug": "6-days-2017", "year": 2017, "rating": 6.2, "runtime": 94, "genres": ["Action", "Drama", "History", "Thriller"], "summary": "In April 1980, armed gunmen stormed the Iranian Embassy in Princes Gate, London and took all inside hostage. Over the next six days a tense standoff took place, all the while a group of highly trained soldiers from the SAS prepared for a raid the world had never seen.", "description_full": "In April 1980, armed gunmen stormed the Iranian Embassy in Princes Gate, London and took all inside hostage. Over the next six days a tense standoff took place, all the while a group of highly trained soldiers from the SAS prepared for a raid the world had never seen.", "synopsis": "In April 1980, armed gunmen stormed the Iranian Embassy in Princes Gate, London and took all inside hostage. Over the next six days a tense standoff took place, all the while a group of highly trained soldiers from the SAS prepared for a raid the world had never seen.", "yt_trailer_code": "ndLJhJgDwI8", "language": "en", "mpa_rating": "R", "background_image": "https://yts.mx/assets/images/movies/6_days_2017/background.jpg", "background_image_original": "https://yts.mx/assets/images/movies/6_days_2017/background.jpg", "small_cover_image": "https://yts.mx/assets/images/movies/6_days_2017/small-cover.jpg", "medium_cover_image": "https://yts.mx/assets/images/movies/6_days_2017/medium-cover.jpg", "state": "ok", "torrents": [{"url": "https://yts.mx/torrent/download/95A452632FF41F64DC958D513694B3FC0B6D6835", "hash": "95A452632FF41F64DC958D513694B3FC0B6D6835", "quality": "720p", "seeds": 30, "peers": 7, "size": "697.7 MB", "size_bytes": 731591475, "date_uploaded": "2017-10-04 15:45:49", "date_uploaded_unix": 1507124749}, {"url": "https://yts.mx/torrent/download/52F95DD4D5F0AA95237AEA81F25B851193BAC75D", "hash": "52F95DD4D5F0AA95237AEA81F25B851193BAC75D", "quality": "1080p", "seeds": 38, "peers": 1, "size": "1.44 GB", "size_bytes": 1546188227, "date_uploaded": "2017-10-04 18:56:05", "date_uploaded_unix": 1507136165}], "date_uploaded": "2017-10-04 15:45:49", "date_uploaded_unix": 1507124749}, {"id": 13470, "url": "https://yts.mx/movies/vanish-2015", "imdb_code": "tt3058674", "title": "VANish", "title_english": "VANish", "title_long": "VANish (2015)", "slug": "vanish-2015", "year": 2015, "rating": 5.1, "runtime": 79, "genres": ["Action", "Crime", "Horror", "Thriller"], "summary": "A kidnapped young woman is forced on a road trip full of murder and mayhem that takes place entirely in her captor's getaway van.", "description_full": "A kidnapped young woman is forced on a road trip full of murder and mayhem that takes place entirely in her captor's getaway van.", "synopsis": "A kidnapped young woman is forced on a road trip full of murder and mayhem that takes place entirely in her captor's getaway van.", "yt_trailer_code": "j6e6Nc1emwg", "language": "en", "mpa_rating": "", "background_image": "https://yts.mx/assets/images/movies/vanish_2015/background.jpg", "background_image_original": "https://yts.mx/assets/images/movies/vanish_2015/background.jpg", "small_cover_image": "https://yts.mx/assets/images/movies/vanish_2015/small-cover.jpg", "medium_cover_image": "https://yts.mx/assets/images/movies/vanish_2015/medium-cover.jpg", "state": "ok", "torrents": [{"url": "https://yts.mx/torrent/download/2D9A6277323EC626AFA68C8C03E1CB5549F2F238", "hash": "2D9A6277323EC626AFA68C8C03E1CB5549F2F238", "quality": "720p", "seeds": 1, "peers": 1, "size": "706.95 MB", "size_bytes": 741290803, "date_uploaded": "2019-09-01 13:17:03", "date_uploaded_unix": 1567336623}, {"url": "https://yts.mx/torrent/download/FC71911407C50B6F94A7382EDB849E9F05BAB514", "hash": "FC71911407C50B6F94A7382EDB849E9F05BAB514", "quality": "1080p", "seeds": 3, "peers": 4, "size": "1.25 GB", "size_bytes": 1342177280, "date_uploaded": "2019-09-01 14:44:09", "date_uploaded_unix": 1567341849}], "date_uploaded": "2019-09-01 13:17:03", "date_uploaded_unix": 1567336623}]}}