{"movie_details": {"movie": {"id": 9542, "url": "https://yts.mx/movies/the-equalizer-2-2018", "imdb_code": "tt3766354", "title": "The Equalizer 2", "title_english": "The Equalizer 2", "title_long": "The Equalizer 2 (2018)", "slug": "the-equalizer-2-2018", "year": 2018, "rating": 6.7, "runtime": 121, "genres": ["Action", "Crime", "Thriller"], "download_count": 2955361, "like_count": 441, "description_intro": "Director Antoine Fuqua reunites with Denzel Washington in this sequel to 2014's The Equalizer. Washington resumes his role as Robert McCall: a retired CIA Black Ops operative who now works as a Lyft driver and moonlights as a vigilante. When his long-time friend is murdered he embarks on a relentless, globe-trotting quest for vengeance.", "description_full": "Director Antoine Fuqua reunites with Denzel Washington in this sequel to 2014's The Equalizer. Washington resumes his role as Robert McCall: a retired CIA Black Ops operative who now works as a Lyft driver and moonlights as a vigilante. When his long-time friend is murdered he embarks on a relentless, globe-trotting quest for vengeance.", "yt_trailer_code": "HyNJ3UrGk_I", "language": "en", "mpa_rating": "R", "background_image": "https://yts.mx/assets/images/movies/the_equalizer_2_2018/background.jpg", "background_image_original": "https://yts.mx/assets/images/movies/the_equalizer_2_2018/background.jpg", "small_cover_image": "https://yts.mx/assets/images/movies/the_equalizer_2_2018/small-cover.jpg", "medium_cover_image": "https://yts.mx/assets/images/movies/the_equalizer_2_2018/medium-cover.jpg", "large_cover_image": "https://yts.mx/assets/images/movies/the_equalizer_2_2018/large-cover.jpg", "medium_screenshot_image1": "https://yts.mx/assets/images/movies/the_equalizer_2_2018/medium-screenshot1.jpg", "medium_screenshot_image2": "https://yts.mx/assets/images/movies/the_equalizer_2_2018/medium-screenshot2.jpg", "medium_screenshot_image3": "https://yts.mx/assets/images/movies/the_equalizer_2_2018/medium-screenshot3.jpg", "large_screenshot_image1": "https://yts.mx/assets/images/movies/the_equalizer_2_2018/large-screenshot1.jpg", "large_screenshot_image2": "https://yts.mx/assets/images/movies/the_equalizer_2_2018/large-screenshot2.jpg", "large_screenshot_image3": "https://yts.mx/assets/images/movies/the_equalizer_2_2018/large-screenshot3.jpg", "cast": [{"name": "Bill Pullman", "character_name": "Brian Plummer", "url_small_image": "https://yts.mx/assets/images/actors/thumb/nm0000597.jpg", "imdb_code": "0000597"}, {"name": "Melissa Leo", "character_name": "Susan Plummer", "url_small_image": "https://yts.mx/assets/images/actors/thumb/nm0502425.jpg", "imdb_code": "0502425"}, {"name": "Kimberly Howe", "character_name": "Lyft Girl #2", "imdb_code": "5202431"}, {"name": "Orson Bean", "character_name": "Sam Rubinstein", "imdb_code": "0004730"}], "torrents": [{"url": "https://yts.mx/torrent/download/2EAE46978A12837748DA3057D700791D03B8F7EE", "hash": "2EAE46978A12837748DA3057D700791D03B8F7EE", "quality": "720p", "type": "bluray", "seeds": 212, "peers": 13, "size": "1.02 GB", "size_bytes": 1095216660, "date_uploaded": "2018-11-13 03:23:41", "date_uploaded_unix": 1542075821}, {"url": "https://yts.mx/torrent/download/25FF54CE7780165143F1F6BE427F9321A897E10C", "hash": "25FF54CE7780165143F1F6BE427F9321A897E10C", "quality": "1080p", "type": "bluray", "seeds": 267, "peers": 14, "size": "1.95 GB", "size_bytes": 2093796557, "date_uploaded": "2018-11-13 05:17:41", "date_uploaded_unix": 1542082661}, {"url": "https://yts.mx/torrent/download/8D04B808DA62F5F97E33FDC4B29F4F0A03D86078", "hash": "8D04B808DA62F5F97E33FDC4B29F4F0A03D86078", "quality": "720p", "type": "web", "seeds": 234, "peers": 13, "size": "1.02 GB", "size_bytes": 1095216660, "date_uploaded": "2018-10-30 18:25:54", "date_uploaded_unix": 1540920354}, {"url": "https://yts.mx/torrent/download/54C736C8A78982842550C554BB2E8A21CBB6A4A2", "hash": "54C736C8A78982842550C554BB2E8A21CBB6A4A2", "quality": "1080p", "type": "web", "seeds": 239, "peers": 6, "size": "1.95 GB", "size_bytes": 2093796557, "date_uploaded": "2018-10-30 20:40:52", "date_uploaded_unix": 1540928452}], "date_uploaded": "2018-10-30 18:25:54", "date_uploaded_unix": 1540920354}}, "movie_suggestions": {"movie_count": 4, "movies": [{"id": 22293, "url": "https://yts.mx/movies/carmilla-2019", "imdb_code": "tt7280218", "title": "Carmilla", "title_english": "Carmilla", "title_long": "Carmilla (2019)", "slug": "carmilla-2019", "year": 2019, "rating": 4.9, "runtime": 94, "genres": ["Action", "Drama", "Fantasy", "Romance"], "summary": "An atmospheric, coming-of-age love story steeped in eerie mystery and inspired by the gothic novel of the same name.", "description_full": "An atmospheric, coming-of-age love story steeped in eerie mystery and inspired by the gothic novel of the same name.", "synopsis": "An atmospheric, coming-of-age love story steeped in eerie mystery and inspired by the gothic novel of the same name.", "yt_trailer_code": "rpIhVvOaNi0", "language": "en", "mpa_rating": "", "background_image": "https://yts.mx/assets/images/movies/carmilla_2019/background.jpg", "background_image_original": "https://yts.mx/assets/images/movies/carmilla_2019/background.jpg", "small_cover_image": "https://yts.mx/assets/images/movies/carmilla_2019/small-cover.jpg", "medium_cover_image": "https://yts.mx/assets/images/movies/carmilla_2019/medium-cover.jpg", "state": "ok", "torrents": [{"url": "https://yts.mx/torrent/download/2C3E46296923D87EF95C0186ECC9D168FC1603D6", "hash": "2C3E46296923D87EF95C0186ECC9D168FC1603D6", "quality": "720p", "seeds": 7, "peers": 1, "size": "862.7 MB", "size_bytes": 904606515, "date_uploaded": "2020-10-15 21:55:13", "date_uploaded_unix": 1602791713}, {"url": "https://yts.mx/torrent/download/CBD37903F4A55F190AA48B5BF145A24486A7B21E", "hash": "CBD37903F4A55F190AA48B5BF145A24486A7B21E", "quality": "1080p", "seeds": 2, "peers": 0, "size": "1.73 GB", "size_bytes": 1857573356, "date_uploaded": "2020-10-16 00:03:30", "date_uploaded_unix": 1602799410}], "date_uploaded": "2020-10-15 21:55:13", "date_uploaded_unix": 1602791713}, {"id": 6203, "url": "https://yts.mx/movies/very-bad-things-1998", "imdb_code": "tt0124198", "title": "Very Bad Things", "title_english": "Very Bad Things", "title_long": "Very Bad Things (1998)", "slug": "very-bad-things-1998", "year": 1998, "rating": 6.4, "runtime": 100, "genres": ["Action", "Comedy", "Crime", "Thriller"], "summary": "A group of friends head to Las Vegas for a bachelor party.. only things go wrong and a woman is killed. Soon, the bodies are piling up and the friends find themselves turning against one another as the coverup builds.", "description_full": "A group of friends head to Las Vegas for a bachelor party.. only things go wrong and a woman is killed. Soon, the bodies are piling up and the friends find themselves turning against one another as the coverup builds.", "synopsis": "A group of friends head to Las Vegas for a bachelor party.. only things go wrong and a woman is killed. Soon, the bodies are piling up and the friends find themselves turning against one another as the coverup builds.", "yt_trailer_code": "WUIO3LKZcdI", "language": "en", "mpa_rating": "R", "background_image": "https://yts.mx/assets/images/movies/very_bad_things_1998/background.jpg", "background_image_original": "https://yts.mx/assets/images/movies/very_bad_things_1998/background.jpg", "small_cover_image": "https://yts.mx/assets/images/movies/very_bad_things_1998/small-cover.jpg", "medium_cover_image": "https://yts.mx/assets/images/movies/very_bad_things_1998/medium-cover.jpg", "state": "ok", "torrents": [{"url": "https://yts.mx/torrent/download/C75BD01B52BBE3AA17D84C18F10844C88E66C12B", "hash": "C75BD01B52BBE3AA17D84C18F10844C88E66C12B", "quality": "720p", "seeds": 13, "peers": 5, "size": "737.88 MB", "size_bytes": 773723259, "date_uploaded": "2016-12-01 03:17:11", "date_uploaded_unix": 1480558631}, {"url": "https://yts.mx/torrent/download/8562F82FFF54C0CAF3EE8D8A2F3C2D225F0D67D7", "hash": "8562F82FFF54C0CAF3EE8D8A2F3C2D225F0D67D7", "quality": "1080p", "seeds": 15, "peers": 3, "size": "1.53 GB", "size_bytes": 1642824991, "date_uploaded": "2016-12-01 05:37:12", "date_uploaded_unix": 1480567032}], "date_uploaded": "2016-12-01 03:17:11", "date_uploaded_unix": 1480558631}, {"id": 2164, "url": "https://yts.mx/movies/new-years-eve-2011", "imdb_code": "tt1598822", "title": "New Year's Eve", "title_english": "New Year's Eve", "title_long": "New Year's Eve (2011)", "slug": "new-years-eve-2011", "year": 2011, "rating": 5.7, "runtime": 118, "genres": ["Action", "Comedy", "Romance"], "summary": "Set during New Year's Eve in New York city, this movie follows several people and how the day affects them. Kim is a single mother who still thinks of her daughter, Hailey as a child who wants to go out with a boy so that she could kiss him at midnight. Claire, who is in charge of the city's annual tradition, the ball drop on Times Square. And when something goes wrong she has to ask an electrician, who was fired, to come and fix it. Laura, a chef who is cooking the New year's Eve party for a record company who runs into Jensen, her ex who's a singer and performing at the party. While he tries to apologize for how things ended, she refuses to accept it. Ingrid, a woman who works at the record company, after having a near death experience, decides to quit her job and asks a young messenger, Paul to help her fulfill her resolutions. And at a hospital, Stan, a man who is in the final stages of cancer, only wishes to see the ball drop. Also Griffin and Tess, a couple who are expecting, ...", "description_full": "Set during New Year's Eve in New York city, this movie follows several people and how the day affects them. Kim is a single mother who still thinks of her daughter, Hailey as a child who wants to go out with a boy so that she could kiss him at midnight. Claire, who is in charge of the city's annual tradition, the ball drop on Times Square. And when something goes wrong she has to ask an electrician, who was fired, to come and fix it. Laura, a chef who is cooking the New year's Eve party for a record company who runs into Jensen, her ex who's a singer and performing at the party. While he tries to apologize for how things ended, she refuses to accept it. Ingrid, a woman who works at the record company, after having a near death experience, decides to quit her job and asks a young messenger, Paul to help her fulfill her resolutions. And at a hospital, Stan, a man who is in the final stages of cancer, only wishes to see the ball drop. Also Griffin and Tess, a couple who are expecting, ...", "synopsis": "Set during New Year's Eve in New York city, this movie follows several people and how the day affects them. Kim is a single mother who still thinks of her daughter, Hailey as a child who wants to go out with a boy so that she could kiss him at midnight. Claire, who is in charge of the city's annual tradition, the ball drop on Times Square. And when something goes wrong she has to ask an electrician, who was fired, to come and fix it. Laura, a chef who is cooking the New year's Eve party for a record company who runs into Jensen, her ex who's a singer and performing at the party. While he tries to apologize for how things ended, she refuses to accept it. Ingrid, a woman who works at the record company, after having a near death experience, decides to quit her job and asks a young messenger, Paul to help her fulfill her resolutions. And at a hospital, Stan, a man who is in the final stages of cancer, only wishes to see the ball drop. Also Griffin and Tess, a couple who are expecting, ...", "yt_trailer_code": "pnDzKi5j_9Q", "language": "en", "mpa_rating": "PG-13", "background_image": "https://yts.mx/assets/images/movies/New_Year_s_Eve_2011/background.jpg", "background_image_original": "https://yts.mx/assets/images/movies/New_Year_s_Eve_2011/background.jpg", "small_cover_image": "https://yts.mx/assets/images/movies/New_Year_s_Eve_2011/small-cover.jpg", "medium_cover_image": "https://yts.mx/assets/images/movies/New_Year_s_Eve_2011/medium-cover.jpg", "state": "ok", "torrents": [{"url": "https://yts.mx/torrent/download/86DD870B395EAC1E92C6AE0AB5DA9336594AF826", "hash": "86DD870B395EAC1E92C6AE0AB5DA9336594AF826", "quality": "720p", "seeds": 7, "peers": 3, "size": "750.47 MB", "size_bytes": 786924831, "date_uploaded": "2015-11-01 01:22:32", "date_uploaded_unix": 1446337352}, {"url": "https://yts.mx/torrent/download/2153FA1325AD0BD81420D4D4E9FD4A24DFB16A6E", "hash": "2153FA1325AD0BD81420D4D4E9FD4A24DFB16A6E", "quality": "1080p", "seeds": 10, "peers": 4, "size": "1.40 GB", "size_bytes": 1503238554, "date_uploaded": "2015-11-01 01:22:34", "date_uploaded_unix": 1446337354}], "date_uploaded": "2015-11-01 01:22:32", "date_uploaded_unix": 1446337352}, {"id": 2483, "url": "https://yts.mx/movies/red-dawn-1984", "imdb_code": "tt0087985", "title": "Red Dawn", "title_english": "Red Dawn", "title_long": "Red Dawn (1984)", "slug": "red-dawn-1984", "year": 1984, "rating": 6.4, "runtime": 114, "genres": ["Action", "Drama", "War"], "summary": "From out of the sky, Soviet, Nicaraguan, and Cuban troops begin landing on the football field of a Colorado high school. In a few seconds, the paratroopers have attacked the school and sent a group of teenagers fleeing into the mountains. Armed only with hunting rifles, pistols, and bows and arrows, the teens struggle to survive the bitter winter and the Soviet K.G.B. patrols hunting for them. Eventually, trouble arises when they kill a group of Soviet soldiers on patrol in the highlands. Soon they will wage their own guerrilla warfare against the invading Soviet troops under the banner of \"Wolverines!\"", "description_full": "From out of the sky, Soviet, Nicaraguan, and Cuban troops begin landing on the football field of a Colorado high school. In a few seconds, the paratroopers have attacked the school and sent a group of teenagers fleeing into the mountains. Armed only with hunting rifles, pistols, and bows and arrows, the teens struggle to survive the bitter winter and the Soviet K.G.B. patrols hunting for them. Eventually, trouble arises when they kill a group of Soviet soldiers on patrol in the highlands. Soon they will wage their own guerrilla warfare against the invading Soviet troops under the banner of \"Wolverines!\"", "synopsis": "From out of the sky, Soviet, Nicaraguan, and Cuban troops begin landing on the football field of a Colorado high school. In a few seconds, the paratroopers have attacked the school and sent a group of teenagers fleeing into the mountains. Armed only with hunting rifles, pistols, and bows and arrows, the teens struggle to survive the bitter winter and the Soviet K.G.B. patrols hunting for them. Eventually, trouble arises when they kill a group of Soviet soldiers on patrol in the highlands. Soon they will wage their own guerrilla warfare against the invading Soviet troops under the banner of \"Wolverines!\"", "yt_trailer_code": "kZLLKwFpFG4", "language": "en", "mpa_rating": "", "background_image": "https://yts.mx/assets/images/movies/Red_Dawn_1984/background.jpg", "background_image_original": "https://yts.mx/assets/images/movies/Red_Dawn_1984/background.jpg", "small_cover_image": "https://yts.mx/assets/images/movies/Red_Dawn_1984/small-cover.jpg", "medium_cover_image": "https://yts.mx/assets/images/movies/Red_Dawn_1984/medium-cover.jpg", "state": "ok", "torrents": [{"url": "https://yts.mx/torrent/download/62A329F2E0A7D4A96F780DED22CF1EC1DF5349E6", "hash": "62A329F2E0A7D4A96F780DED22CF1EC1DF5349E6", "quality": "720p", "seeds": 7, "peers": 3, "size": "750.26 MB", "size_bytes": 786704630, "date_uploaded": "2015-11-01 01:58:03", "date_uploaded_unix": 1446339483}, {"url": "https://yts.mx/torrent/download/19A7F9C30E0B415F3C6A0FF9F9AD880BEDEA1623", "hash": "19A7F9C30E0B415F3C6A0FF9F9AD880BEDEA1623", "quality": "1080p", "seeds": 20, "peers": 3, "size": "1.50 GB", "size_bytes": 1610612736, "date_uploaded": "2015-11-01 01:58:06", "date_uploaded_unix": 1446339486}], "date_uploaded": "2015-11-01 01:58:03", "date_uploaded_unix": 1446339483}]}}